pyliburo/__init__.py
pyliburo/analysisrulepalette.py
pyliburo/buildingformeval.py
pyliburo/citygml2eval.py
pyliburo/gml3dmodel.py
pyliburo/gmlparameterise.py
pyliburo/gmlparmpalette.py
pyliburo/massing2citygml.py
pyliburo/runopt.py
pyliburo/shapeattributes.py
pyliburo/shp2citygml.py
pyliburo/skyviewfactor.py
pyliburo/templaterulepalette.py
pyliburo/urbanformeval.py
pyliburo/utility.py
pyliburo/utility3d.py
pyliburo/databases/ettv/ettv_correctionfactor_wall.csv
pyliburo/databases/ettv/retv_correctionfactor_wall.csv
pyliburo/databases/ettv/rttv_correctionfactor_roof.csv
pyliburo/databases/ettv/wall_uvalue.csv
pyliburo/databases/ettv/win_uvalue.csv
pyliburo/py2energyplus/__init__.py
pyliburo/py2energyplus/idf_writer.py
pyliburo/py2radiance/__init__.py
pyliburo/py2radiance/write_rad.py
pyliburo/py3dmodel/__init__.py
pyliburo/py3dmodel/calculate.py
pyliburo/py3dmodel/construct.py
pyliburo/py3dmodel/fetch.py
pyliburo/py3dmodel/modify.py
pyliburo/py3dmodel/OCCUtils/Common.py
pyliburo/py3dmodel/OCCUtils/Construct.py
pyliburo/py3dmodel/OCCUtils/Image.py
pyliburo/py3dmodel/OCCUtils/Iteration.py
pyliburo/py3dmodel/OCCUtils/Topology.py
pyliburo/py3dmodel/OCCUtils/__init__.py
pyliburo/py3dmodel/OCCUtils/base.py
pyliburo/py3dmodel/OCCUtils/edge.py
pyliburo/py3dmodel/OCCUtils/face.py
pyliburo/py3dmodel/OCCUtils/shell.py
pyliburo/py3dmodel/OCCUtils/solid.py
pyliburo/py3dmodel/OCCUtils/types_lut.py
pyliburo/py3dmodel/OCCUtils/vertex.py
pyliburo/py3dmodel/OCCUtils/wire.py
pyliburo/pycitygml/__init__.py
pyliburo/pycitygml/gmlgeometry.py
pyliburo/pycitygml/write_gml.py
pyliburo/pycitygml/write_gmlgeometry.py
pyliburo/pyoptimise/__init__.py
pyliburo/pyoptimise/analyse_xml.py
pyliburo/pyoptimise/draw_graph.py
pyliburo/pyoptimise/nsga2.py
pyliburo-0.12.dist-info/DESCRIPTION.rst
pyliburo-0.12.dist-info/METADATA
pyliburo-0.12.dist-info/RECORD
pyliburo-0.12.dist-info/WHEEL
pyliburo-0.12.dist-info/metadata.json
pyliburo-0.12.dist-info/top_level.txt
